ordir/__init__.py
ordir-1.0.1.dist-info/METADATA
ordir-1.0.1.dist-info/WHEEL
ordir-1.0.1.dist-info/top_level.txt
ordir-1.0.1.dist-info/RECORD
