Metadata-Version: 2.1
Name: ordir
Version: 1.0.1
Summary: Print __dir__ in a readable format
Home-page: https://github.com/josephhaaga/ordir
Author: Joseph Haaga
Author-email: haaga.joe@gmail.com
License: MIT
Platform: UNKNOWN
Classifier: License :: OSI Approved :: MIT License
Classifier: Programming Language :: Python :: 3
Classifier: Programming Language :: Python :: 3.7
